markovmodus/__init__.py
markovmodus/api.py
markovmodus/config.py
markovmodus/io.py
markovmodus/simulation.py
markovmodus/viz/.gitkeep
markovmodus/viz/__init__.py
markovmodus-0.1.0.dist-info/METADATA
markovmodus-0.1.0.dist-info/WHEEL
markovmodus-0.1.0.dist-info/licenses/LICENSE
markovmodus-0.1.0.dist-info/RECORD
