Metadata-Version: 2.4
Name: markovmodus
Version: 0.1.0
Summary: Markov-modulated ODE simulator for synthetic single-cell splicing datasets.
Project-URL: Homepage, https://github.com/subthaumic/markovmodus
Project-URL: Repository, https://github.com/subthaumic/markovmodus
Project-URL: Issues, https://github.com/subthaumic/markovmodus/issues
Project-URL: Changelog, https://subthaumic.github.io/markovmodus/changelog.html
Project-URL: Documentation, https://subthaumic.github.io/markovmodus/
Author: Michael Bleher
License-Expression: MIT
License-File: LICENSE
Keywords: markov,rna,simulation,single-cell,splicing
Classifier: Intended Audience :: Science/Research
Classifier: License :: OSI Approved :: MIT License
Classifier: Programming Language :: Python
Classifier: Programming Language :: Python :: 3
Classifier: Programming Language :: Python :: 3.10
Classifier: Programming Language :: Python :: 3.11
Classifier: Programming Language :: Python :: 3.12
Classifier: Topic :: Scientific/Engineering :: Bio-Informatics
Requires-Python: >=3.10
Requires-Dist: anndata>=0.9
Requires-Dist: numpy>=1.23
Requires-Dist: pandas>=2.0
Provides-Extra: dev
Requires-Dist: build>=1.2; extra == 'dev'
Requires-Dist: furo>=2024.5.27; extra == 'dev'
Requires-Dist: mypy>=1.5; extra == 'dev'
Requires-Dist: myst-parser>=2.0; extra == 'dev'
Requires-Dist: pre-commit>=3.7; extra == 'dev'
Requires-Dist: pytest-cov>=4.1; extra == 'dev'
Requires-Dist: pytest>=7.4; extra == 'dev'
Requires-Dist: ruff>=0.1.8; extra == 'dev'
Requires-Dist: sphinx>=7.2; extra == 'dev'
Requires-Dist: twine>=4.0; extra == 'dev'
Provides-Extra: docs
Requires-Dist: furo>=2024.5.27; extra == 'docs'
Requires-Dist: myst-parser>=2.0; extra == 'docs'
Requires-Dist: sphinx-autobuild>=2021.3.14; extra == 'docs'
Requires-Dist: sphinx>=7.2; extra == 'docs'
Provides-Extra: test
Requires-Dist: pytest-cov>=4.1; extra == 'test'
Requires-Dist: pytest>=7.4; extra == 'test'
